MANIFEST.in
README.txt
setup.cfg
setup.py
tgext/__init__.py
tgext.admin.egg-info/PKG-INFO
tgext.admin.egg-info/SOURCES.txt
tgext.admin.egg-info/dependency_links.txt
tgext.admin.egg-info/entry_points.txt
tgext.admin.egg-info/namespace_packages.txt
tgext.admin.egg-info/not-zip-safe
tgext.admin.egg-info/pbr.json
tgext.admin.egg-info/requires.txt
tgext.admin.egg-info/top_level.txt
tgext/admin/__init__.py
tgext/admin/config.py
tgext/admin/controller.py
tgext/admin/layouts.py
tgext/admin/mongo.py
tgext/admin/tgadminconfig.py
tgext/admin/utils.py
tgext/admin/widgets.py
tgext/admin/templates/__init__.py
tgext/admin/templates/bootstrap_form_layout.html
tgext/admin/templates/bootstrap_form_layout.jinja
tgext/admin/templates/bootstrap_form_layout.kajiki
tgext/admin/templates/bootstrap_form_layout.mak
tgext/admin/templates/bootstrap_grouped_index.html
tgext/admin/templates/bootstrap_grouped_index.xhtml
tgext/admin/templates/bootstrap_index.html
tgext/admin/templates/bootstrap_index.jinja
tgext/admin/templates/bootstrap_index.mak
tgext/admin/templates/bootstrap_index.xhtml
tgext/admin/templates/index.html
tgext/admin/templates/index.jinja
tgext/admin/templates/index.mak
tgext/admin/templates/index.xhtml
tgext/admin/templates/bootstrap_crud/__init__.py
tgext/admin/templates/bootstrap_crud/edit.html
tgext/admin/templates/bootstrap_crud/edit.jinja
tgext/admin/templates/bootstrap_crud/edit.mak
tgext/admin/templates/bootstrap_crud/edit.xhtml
tgext/admin/templates/bootstrap_crud/get_all.html
tgext/admin/templates/bootstrap_crud/get_all.jinja
tgext/admin/templates/bootstrap_crud/get_all.mak
tgext/admin/templates/bootstrap_crud/get_all.xhtml
tgext/admin/templates/bootstrap_crud/new.html
tgext/admin/templates/bootstrap_crud/new.jinja
tgext/admin/templates/bootstrap_crud/new.mak
tgext/admin/templates/bootstrap_crud/new.xhtml