Metadata-Version: 1.1
Name: tgext.admin
Version: 0.7.2
Summary: Admin Controller add-on for basic TG identity model.
Home-page: https://github.com/TurboGears/tgext.admin
Author: Christopher Perkins
Author-email: chris@percious.com
License: MIT
Keywords: turbogears2.extension,TG2,TG,sprox,Rest,internet,admin
Platform: UNKNOWN
Classifier: Programming Language :: Python
Classifier: Topic :: Software Development :: Libraries :: Python Modules
